SecureTool/Password.py
SecureTool/Scanning.py
SecureTool/Scraping.py
SecureTool/__init__.py
securetool-2.0.0.dist-info/licenses/LICENSE
securetool-2.0.0.dist-info/METADATA
securetool-2.0.0.dist-info/WHEEL
securetool-2.0.0.dist-info/top_level.txt
securetool-2.0.0.dist-info/RECORD
