Metadata-Version: 2.4
Name: SecureTool
Version: 2.0.0
Summary: Comprehensive cybersecurity tools including network scanning, password strength checking, and web scraping.
Home-page: https://github.com/alanhasn/my_cybersec_lib
Author: WhoamiAlan
Author-email: whoamialan11@gmail.com
Classifier: Programming Language :: Python :: 3
Classifier: License :: OSI Approved :: MIT License
Classifier: Operating System :: OS Independent
Classifier: Topic :: Security :: Cryptography
Classifier: Topic :: Utilities
Requires-Python: >=3.6
License-File: LICENSE
Requires-Dist: python-nmap
Dynamic: author
Dynamic: author-email
Dynamic: classifier
Dynamic: description
Dynamic: description-content-type
Dynamic: home-page
Dynamic: license-file
Dynamic: requires-dist
Dynamic: requires-python
Dynamic: summary
